PytopiaAPI/__init__.py
PytopiaAPI-1.0.4.dist-info/LICENSE
PytopiaAPI-1.0.4.dist-info/METADATA
PytopiaAPI-1.0.4.dist-info/WHEEL
PytopiaAPI-1.0.4.dist-info/top_level.txt
PytopiaAPI-1.0.4.dist-info/RECORD
